overlay_dx/__init__.py
overlay_dx/_version.py
overlay_dx/metrics.py
overlay_dx-0.1.0.dist-info/licenses/LICENSE
overlay_dx-0.1.0.dist-info/METADATA
overlay_dx-0.1.0.dist-info/WHEEL
overlay_dx-0.1.0.dist-info/top_level.txt
overlay_dx-0.1.0.dist-info/RECORD
