Metadata-Version: 2.4
Name: overlay-dx
Version: 0.1.0
Summary: Visual and quantitative metric for evaluating time series forecasts
Author-email: Smile R&D Team <rnd@smile.fr>
Maintainer-email: "Long H. Ngo" <rnd@smile.fr>, Mohammed Amine Chamli <rnd@smile.fr>, Jonathan Rivalan <rnd@smile.fr>
Project-URL: Homepage, https://github.com/Smile-SA/overlay_dx
Project-URL: Documentation, https://github.com/Smile-SA/overlay_dx#readme
Project-URL: Repository, https://github.com/Smile-SA/overlay_dx
Project-URL: Bug Tracker, https://github.com/Smile-SA/overlay_dx/issues
Project-URL: Research Paper, https://ola2025.sciencesconf.org/
Keywords: machine learning,forecasting,time series,evaluation,metrics,scikit-learn,overlay
Classifier: Development Status :: 4 - Beta
Classifier: Intended Audience :: Developers
Classifier: Intended Audience :: Science/Research
Classifier: Operating System :: OS Independent
Classifier: Programming Language :: Python :: 3
Classifier: Programming Language :: Python :: 3.8
Classifier: Programming Language :: Python :: 3.9
Classifier: Programming Language :: Python :: 3.10
Classifier: Programming Language :: Python :: 3.11
Classifier: Programming Language :: Python :: 3.12
Classifier: Topic :: Scientific/Engineering :: Artificial Intelligence
Classifier: Topic :: Scientific/Engineering :: Information Analysis
Requires-Python: >=3.8
License-File: LICENSE
Requires-Dist: numpy>=1.20.0
Requires-Dist: scikit-learn>=1.0.0
Requires-Dist: matplotlib>=3.3.0
Provides-Extra: dev
Requires-Dist: pytest>=7.0; extra == "dev"
Requires-Dist: pytest-cov>=4.0; extra == "dev"
Requires-Dist: flake8>=5.0; extra == "dev"
Dynamic: license-file
